{
  "$schema": "https://json-schema.org/draft/2020-12/schema",
  "$id": "https://raw.githubusercontent.com/api-evangelist/toast-tab/refs/heads/main/json-schema/menus-height-schema.json",
  "title": "Height",
  "description": "The height of the item or modifier. Use the `dimensionUnitOfMeasure` value to determine the unit of measurement.\n\nThe `height` value is `null` if no height is specified for the item or modifier.\n\nYou can use the `length`, `height`, and `width` values to determine the overall size of the item or modifier. This information is useful, for example, when determining shipping costs or choosing the size of delivery vehicle to use.\n",
  "type": "number",
  "format": "float"
}